kmp_util.cp313-win_amd64.pyd
kmp_util-1.0.3.dist-info/LICENSE
kmp_util-1.0.3.dist-info/METADATA
kmp_util-1.0.3.dist-info/WHEEL
kmp_util-1.0.3.dist-info/top_level.txt
kmp_util-1.0.3.dist-info/RECORD
