Metadata-Version: 2.1
Name: kmp-util
Version: 1.0.3
Summary: A module providing KMP-based search for strings and bytes.
Home-page: https://github.com/qfcy/py-kmp-util
Author: qfcy
Author-email: 3076711200@qq.com
License: UNKNOWN
Keywords: kmp,string,algorithm
Platform: UNKNOWN
